[
  {
    "questionId": "who_overthinks_everything",
    "text": "Wer denkt 체ber alles zu viel nach?",
    "category": "inner_monologue"
  },
  {
    "questionId": "who_has_most_elaborate_daydreams",
    "text": "Wer hat die ausgefeiltesten Tagtr채ume?",
    "category": "inner_monologue"
  },
  {
    "questionId": "who_argues_with_themselves",
    "text": "Wer streitet mit sich selbst?",
    "category": "inner_monologue"
  },
  {
    "questionId": "who_has_craziest_thoughts",
    "text": "Wer hat die verr체cktesten Gedanken?",
    "category": "inner_monologue"
  },
  {
    "questionId": "who_rehearses_conversations_in_head",
    "text": "Wer probt Gespr채che im Kopf?",
    "category": "inner_monologue"
  },
  {
    "questionId": "who_creates_alternate_scenarios",
    "text": "Wer erschafft alternative Szenarien?",
    "category": "inner_monologue"
  }
]