[
  {
    "questionId": "wer_kommentiert_alles_was_ihm_in_den_feed_kommt",
    "text": "Wer kommentiert alles, was ihm in den Feed kommt?",
    "category": "Im Internet"
  },
  {
    "questionId": "wer_hat_schon_mal_aus_versehen_ein_altes_foto_geli",
    "text": "Wer hat schon mal aus Versehen ein altes Foto geliket?",
    "category": "Im Internet"
  },
  {
    "questionId": "wer_teilt_die_meisten_memes",
    "text": "Wer teilt die meisten Memes?",
    "category": "Im Internet"
  },
  {
    "questionId": "wer_googelt_jede_kleinigkeit_sofort",
    "text": "Wer googelt jede Kleinigkeit sofort?",
    "category": "Im Internet"
  },
  {
    "questionId": "wer_hat_das_peinlichste_profilbild",
    "text": "Wer hat das peinlichste Profilbild?",
    "category": "Im Internet"
  },
  {
    "questionId": "wer_liest_kommentare_und_antwortet_wutend",
    "text": "Wer liest Kommentare – und antwortet wütend?",
    "category": "Im Internet"
  },
  {
    "questionId": "wer_stalkt_still_aber_grundlich",
    "text": "Wer stalkt still, aber gründlich?",
    "category": "Im Internet"
  },
  {
    "questionId": "wer_hat_schon_mal_was_super_peinliches_gepostet_un",
    "text": "Wer hat schon mal was super Peinliches gepostet und gelöscht?",
    "category": "Im Internet"
  },
  {
    "questionId": "wer_gibt_sich_online_komplett_anders",
    "text": "Wer gibt sich online komplett anders?",
    "category": "Im Internet"
  },
  {
    "questionId": "wer_postet_storys_aus_dem_supermarkt",
    "text": "Wer postet Storys aus dem Supermarkt?",
    "category": "Im Internet"
  },
  {
    "questionId": "wer_hat_einen_onlinewarenkorb_voller_dinge_die_er_",
    "text": "Wer hat einen Online-Warenkorb voller Dinge, die er nie kauft?",
    "category": "Im Internet"
  },
  {
    "questionId": "wer_kommentiert_unter_promiposts_als_waren_sie_fre",
    "text": "Wer kommentiert unter Promi-Posts, als wären sie Freunde?",
    "category": "Im Internet"
  },
  {
    "questionId": "wer_postet_urlaubsbilder_aus_dem_letzten_jahr_als_",
    "text": "Wer postet Urlaubsbilder aus dem letzten Jahr als „Throwback“?",
    "category": "Im Internet"
  },
  {
    "questionId": "wer_hat_mehr_follower_als_echte_freunde",
    "text": "Wer hat mehr Follower als echte Freunde?",
    "category": "Im Internet"
  },
  {
    "questionId": "wer_macht_aus_jedem_like_ein_event",
    "text": "Wer macht aus jedem Like ein Event?",
    "category": "Im Internet"
  },
  {
    "questionId": "wer_hat_schon_mal_einen_shitstorm_ausgelost_aus_ve",
    "text": "Wer hat schon mal einen Shitstorm ausgelöst – aus Versehen?",
    "category": "Im Internet"
  },
  {
    "questionId": "wer_postet_screenshots_von_chats_mit_emojizensur",
    "text": "Wer postet Screenshots von Chats – mit Emoji-Zensur?",
    "category": "Im Internet"
  },
  {
    "questionId": "wer_hat_ein_profilbild_das_10_jahre_alt_ist",
    "text": "Wer hat ein Profilbild, das 10 Jahre alt ist?",
    "category": "Im Internet"
  },
  {
    "questionId": "wer_schreibt_rezensionen_fur_produkte_die_er_nie_g",
    "text": "Wer schreibt Rezensionen für Produkte, die er nie gekauft hat?",
    "category": "Im Internet"
  },
  {
    "questionId": "wer_hat_eine_playlist_fur_jede_lebenslage_und_teil",
    "text": "Wer hat eine Playlist für jede Lebenslage – und teilt sie ungefragt?",
    "category": "Im Internet"
  },
  {
    "questionId": "wer_hat_einen_blog_uber_dinge_die_niemand_versteht",
    "text": "Wer hat einen Blog über Dinge, die niemand versteht?",
    "category": "Im Internet"
  },
  {
    "questionId": "wer_verschickt_kettenbriefe_aus_nostalgie",
    "text": "Wer verschickt Kettenbriefe – aus Nostalgie?",
    "category": "Im Internet"
  },
  {
    "questionId": "wer_hat_einen_onlinefreund_den_niemand_kennt",
    "text": "Wer hat einen Online-Freund, den niemand kennt?",
    "category": "Im Internet"
  },
  {
    "questionId": "wer_kommentiert_eigene_posts_um_diskussionen_zu_st",
    "text": "Wer kommentiert eigene Posts, um Diskussionen zu starten?",
    "category": "Im Internet"
  },
  {
    "questionId": "wer_hat_schon_mal_einen_livestream_gemacht_fur_sic",
    "text": "Wer hat schon mal einen Livestream gemacht – für sich selbst?",
    "category": "Im Internet"
  },
  {
    "questionId": "wer_hat_ein_memearchiv_auf_dem_handy",
    "text": "Wer hat ein Meme-Archiv auf dem Handy?",
    "category": "Im Internet"
  },
  {
    "questionId": "wer_postet_foodpics_die_aussehen_wie_kunstwerke",
    "text": "Wer postet Foodpics, die aussehen wie Kunstwerke?",
    "category": "Im Internet"
  },
  {
    "questionId": "wer_hat_einen_geheimen_tiktokaccount",
    "text": "Wer hat einen geheimen TikTok-Account?",
    "category": "Im Internet"
  },
  {
    "questionId": "wer_liked_alles_um_nicht_aufzufallen",
    "text": "Wer liked alles, um nicht aufzufallen?",
    "category": "Im Internet"
  },
  {
    "questionId": "wer_hat_einen_onlinekalender_aber_vergisst_alle_te",
    "text": "Wer hat einen Online-Kalender, aber vergisst alle Termine?",
    "category": "Im Internet"
  },
  {
    "questionId": "wer_hat_einen_socialmediadetox_versucht_und_ist_ge",
    "text": "Wer hat einen Social-Media-Detox versucht – und ist gescheitert?",
    "category": "Im Internet"
  },
  {
    "questionId": "wer_postet_motivationsspruche_und_halt_sich_nie_da",
    "text": "Wer postet Motivationssprüche – und hält sich nie daran?",
    "category": "Im Internet"
  },
  {
    "questionId": "wer_hat_einen_onlineshop_aber_keine_kunden",
    "text": "Wer hat einen Online-Shop, aber keine Kunden?",
    "category": "Im Internet"
  },
  {
    "questionId": "wer_kommentiert_mit_gifs_die_niemand_versteht",
    "text": "Wer kommentiert mit GIFs, die niemand versteht?",
    "category": "Im Internet"
  },
  {
    "questionId": "wer_hat_einen_onlinecrush_den_er_nie_anschreibt",
    "text": "Wer hat einen Online-Crush, den er nie anschreibt?",
    "category": "Im Internet"
  }
]